{
  "version": 1,
  "language": {
    "name": "Flix",
    "aliases": [],
    "caseInsensitive": false,
    "keywords": {
      "pattern": null,
      "keyword": [
        "case",
        "class",
        "def",
        "else",
        "enum",
        "if",
        "impl",
        "import",
        "in",
        "lat",
        "rel",
        "index",
        "let",
        "match",
        "namespace",
        "switch",
        "type",
        "yield",
        "with"
      ],
      "literal": [
        "true",
        "false"
      ],
      "built_in": [],
      "raw": null
    },
    "contains": [
      {
        "ref": "m1"
      },
      {
        "ref": "m4"
      },
      {
        "ref": "m7"
      },
      {
        "ref": "m8"
      },
      {
        "ref": "m10"
      },
      {
        "ref": "m12"
      }
    ]
  },
  "modes": [
    {
      "id": "m2",
      "scope": "doctag",
      "className": null,
      "begin": {
        "type": "string",
        "source": "[ ]*(?=(TODO|FIXME|NOTE|BUG|OPTIMIZE|HACK|XXX):)"
      },
      "end": {
        "type": "regex",
        "source": "(TODO|FIXME|NOTE|BUG|OPTIMIZE|HACK|XXX):",
        "flags": ""
      },
      "match": null,
      "beginScope": null,
      "endScope": null,
      "contains": [],
      "variants": [],
      "keywords": null,
      "illegal": null,
      "relevance": 0,
      "excludeBegin": true,
      "excludeEnd": false,
      "returnBegin": false,
      "returnEnd": false,
      "endsWithParent": false,
      "endsParent": false,
      "skip": false,
      "subLanguage": null,
      "beginKeywords": null
    },
    {
      "id": "m3",
      "scope": null,
      "className": null,
      "begin": {
        "type": "string",
        "source": "[ ]+((?:I|a|is|so|us|to|at|if|in|it|on|[A-Za-z]+['](d|ve|re|ll|t|s|n)|[A-Za-z]+[-][a-z]+|[A-Za-z][a-z]{2,})[.]?[:]?([.][ ]|[ ])){3}"
      },
      "end": null,
      "match": null,
      "beginScope": null,
      "endScope": null,
      "contains": [],
      "variants": [],
      "keywords": null,
      "illegal": null,
      "relevance": null,
      "excludeBegin": false,
      "excludeEnd": false,
      "returnBegin": false,
      "returnEnd": false,
      "endsWithParent": false,
      "endsParent": false,
      "skip": false,
      "subLanguage": null,
      "beginKeywords": null
    },
    {
      "id": "m1",
      "scope": "comment",
      "className": null,
      "begin": {
        "type": "string",
        "source": "//"
      },
      "end": {
        "type": "string",
        "source": "$"
      },
      "match": null,
      "beginScope": null,
      "endScope": null,
      "contains": [
        {
          "ref": "m2"
        },
        {
          "ref": "m3"
        }
      ],
      "variants": [],
      "keywords": null,
      "illegal": null,
      "relevance": null,
      "excludeBegin": false,
      "excludeEnd": false,
      "returnBegin": false,
      "returnEnd": false,
      "endsWithParent": false,
      "endsParent": false,
      "skip": false,
      "subLanguage": null,
      "beginKeywords": null
    },
    {
      "id": "m5",
      "scope": "doctag",
      "className": null,
      "begin": {
        "type": "string",
        "source": "[ ]*(?=(TODO|FIXME|NOTE|BUG|OPTIMIZE|HACK|XXX):)"
      },
      "end": {
        "type": "regex",
        "source": "(TODO|FIXME|NOTE|BUG|OPTIMIZE|HACK|XXX):",
        "flags": ""
      },
      "match": null,
      "beginScope": null,
      "endScope": null,
      "contains": [],
      "variants": [],
      "keywords": null,
      "illegal": null,
      "relevance": 0,
      "excludeBegin": true,
      "excludeEnd": false,
      "returnBegin": false,
      "returnEnd": false,
      "endsWithParent": false,
      "endsParent": false,
      "skip": false,
      "subLanguage": null,
      "beginKeywords": null
    },
    {
      "id": "m6",
      "scope": null,
      "className": null,
      "begin": {
        "type": "string",
        "source": "[ ]+((?:I|a|is|so|us|to|at|if|in|it|on|[A-Za-z]+['](d|ve|re|ll|t|s|n)|[A-Za-z]+[-][a-z]+|[A-Za-z][a-z]{2,})[.]?[:]?([.][ ]|[ ])){3}"
      },
      "end": null,
      "match": null,
      "beginScope": null,
      "endScope": null,
      "contains": [],
      "variants": [],
      "keywords": null,
      "illegal": null,
      "relevance": null,
      "excludeBegin": false,
      "excludeEnd": false,
      "returnBegin": false,
      "returnEnd": false,
      "endsWithParent": false,
      "endsParent": false,
      "skip": false,
      "subLanguage": null,
      "beginKeywords": null
    },
    {
      "id": "m4",
      "scope": "comment",
      "className": null,
      "begin": {
        "type": "string",
        "source": "/\\*"
      },
      "end": {
        "type": "string",
        "source": "\\*/"
      },
      "match": null,
      "beginScope": null,
      "endScope": null,
      "contains": [
        {
          "ref": "m5"
        },
        {
          "ref": "m6"
        }
      ],
      "variants": [],
      "keywords": null,
      "illegal": null,
      "relevance": null,
      "excludeBegin": false,
      "excludeEnd": false,
      "returnBegin": false,
      "returnEnd": false,
      "endsWithParent": false,
      "endsParent": false,
      "skip": false,
      "subLanguage": null,
      "beginKeywords": null
    },
    {
      "id": "m7",
      "scope": null,
      "className": "string",
      "begin": {
        "type": "regex",
        "source": "'(.|\\\\[xXuU][a-zA-Z0-9]+)'",
        "flags": ""
      },
      "end": null,
      "match": null,
      "beginScope": null,
      "endScope": null,
      "contains": [],
      "variants": [],
      "keywords": null,
      "illegal": null,
      "relevance": null,
      "excludeBegin": false,
      "excludeEnd": false,
      "returnBegin": false,
      "returnEnd": false,
      "endsWithParent": false,
      "endsParent": false,
      "skip": false,
      "subLanguage": null,
      "beginKeywords": null
    },
    {
      "id": "m9",
      "scope": null,
      "className": null,
      "begin": {
        "type": "string",
        "source": "\""
      },
      "end": {
        "type": "string",
        "source": "\""
      },
      "match": null,
      "beginScope": null,
      "endScope": null,
      "contains": [],
      "variants": [],
      "keywords": null,
      "illegal": null,
      "relevance": null,
      "excludeBegin": false,
      "excludeEnd": false,
      "returnBegin": false,
      "returnEnd": false,
      "endsWithParent": false,
      "endsParent": false,
      "skip": false,
      "subLanguage": null,
      "beginKeywords": null
    },
    {
      "id": "m8",
      "scope": null,
      "className": "string",
      "begin": null,
      "end": null,
      "match": null,
      "beginScope": null,
      "endScope": null,
      "contains": [],
      "variants": [
        {
          "ref": "m9"
        }
      ],
      "keywords": null,
      "illegal": null,
      "relevance": null,
      "excludeBegin": false,
      "excludeEnd": false,
      "returnBegin": false,
      "returnEnd": false,
      "endsWithParent": false,
      "endsParent": false,
      "skip": false,
      "subLanguage": null,
      "beginKeywords": null
    },
    {
      "id": "m11",
      "scope": null,
      "className": "title",
      "begin": {
        "type": "regex",
        "source": "[^0-9\\n\\t \"'(),.`{}\\[\\]:;][^\\n\\t \"'(),.`{}\\[\\]:;]+|[^0-9\\n\\t \"'(),.`{}\\[\\]:;=]",
        "flags": ""
      },
      "end": null,
      "match": null,
      "beginScope": null,
      "endScope": null,
      "contains": [],
      "variants": [],
      "keywords": null,
      "illegal": null,
      "relevance": 0,
      "excludeBegin": false,
      "excludeEnd": false,
      "returnBegin": false,
      "returnEnd": false,
      "endsWithParent": false,
      "endsParent": false,
      "skip": false,
      "subLanguage": null,
      "beginKeywords": null
    },
    {
      "id": "m10",
      "scope": null,
      "className": "function",
      "begin": null,
      "end": {
        "type": "regex",
        "source": "[:={\\[(\\n;]",
        "flags": ""
      },
      "match": null,
      "beginScope": null,
      "endScope": null,
      "contains": [
        {
          "ref": "m11"
        }
      ],
      "variants": [],
      "keywords": null,
      "illegal": null,
      "relevance": null,
      "excludeBegin": false,
      "excludeEnd": true,
      "returnBegin": false,
      "returnEnd": false,
      "endsWithParent": false,
      "endsParent": false,
      "skip": false,
      "subLanguage": null,
      "beginKeywords": "def"
    },
    {
      "id": "m12",
      "scope": "number",
      "className": null,
      "begin": {
        "type": "string",
        "source": "(-?)(\\b0[xX][a-fA-F0-9]+|(\\b\\d+(\\.\\d*)?|\\.\\d+)([eE][-+]?\\d+)?)"
      },
      "end": null,
      "match": null,
      "beginScope": null,
      "endScope": null,
      "contains": [],
      "variants": [],
      "keywords": null,
      "illegal": null,
      "relevance": 0,
      "excludeBegin": false,
      "excludeEnd": false,
      "returnBegin": false,
      "returnEnd": false,
      "endsWithParent": false,
      "endsParent": false,
      "skip": false,
      "subLanguage": null,
      "beginKeywords": null
    }
  ]
}
